mypyctionnary/__init__.py
mypyctionnary/mypyctionnary.py
myPyctionnary-0.3.3.dist-info/METADATA
myPyctionnary-0.3.3.dist-info/WHEEL
myPyctionnary-0.3.3.dist-info/top_level.txt
myPyctionnary-0.3.3.dist-info/RECORD
