Metadata-Version: 2.1
Name: myPyctionnary
Version: 0.3.3
Summary: Dictionnary for python
Home-page: https://pyctionnary.readthedocs.io/
Author: M'GHARI Tariq
Author-email: tariqmghari@gmail.com
License: MIT
Platform: UNKNOWN
Classifier: Intended Audience :: Developers
Classifier: License :: OSI Approved :: MIT License
Classifier: Programming Language :: Python
Classifier: Programming Language :: Python :: 3
Classifier: Programming Language :: Python :: 3.6
Classifier: Programming Language :: Python :: 3.7
Classifier: Programming Language :: Python :: 3.8
Classifier: Programming Language :: Python :: 3.9
Classifier: Operating System :: OS Independent
Requires-Dist: bs4
Requires-Dist: requests
